dlclive/__init__.py
dlclive/benchmark.py
dlclive/check_install/check_install.py
dlclive/display.py
dlclive/dlclive.py
dlclive/exceptions.py
dlclive/graph.py
dlclive/pose.py
dlclive/processor/README.md
dlclive/processor/__init__.py
dlclive/processor/kalmanfilter.py
dlclive/processor/processor.py
dlclive/utils.py
dlclive/version.py
deeplabcut_live-1.0.4.dist-info/LICENSE
deeplabcut_live-1.0.4.dist-info/METADATA
deeplabcut_live-1.0.4.dist-info/WHEEL
deeplabcut_live-1.0.4.dist-info/entry_points.txt
deeplabcut_live-1.0.4.dist-info/RECORD
