Metadata-Version: 2.1
Name: deeplabcut-live
Version: 1.0.4
Summary: Class to load exported DeepLabCut networks and perform pose estimation on single frames (from a camera feed)
Home-page: https://github.com/DeepLabCut/DeepLabCut-live
License: AGPL-3.0-or-later
Author: A. & M. Mathis Labs
Author-email: admin@deeplabcut.org
Requires-Python: >=3.7.1,<3.11
Classifier: License :: OSI Approved :: GNU Affero General Public License v3 or later (AGPLv3+)
Classifier: Operating System :: OS Independent
Classifier: Programming Language :: Python :: 3
Classifier: Programming Language :: Python :: 3.8
Classifier: Programming Language :: Python :: 3.9
Classifier: Programming Language :: Python :: 3.10
Classifier: Programming Language :: Python :: 3
Classifier: Programming Language :: Python :: 3.10
Classifier: Programming Language :: Python :: 3.7
Classifier: Programming Language :: Python :: 3.8
Classifier: Programming Language :: Python :: 3.9
Requires-Dist: Pillow (>=8.0.0)
Requires-Dist: colorcet (>=3.0.0,<4.0.0)
Requires-Dist: dlclibrary (>=0.0.2)
Requires-Dist: numpy (>=1.20,<2.0)
Requires-Dist: opencv-python-headless (>=4.5,<5.0)
Requires-Dist: pandas (>=1.3,<2.0)
Requires-Dist: py-cpuinfo (>=5.0.0)
Requires-Dist: ruamel.yaml (>=0.17.20,<0.18.0)
Requires-Dist: tables (>=3.6,<4.0)
Requires-Dist: tensorflow (>=2.7.0,<=2.10)
Requires-Dist: tqdm (>=4.62.3,<5.0.0)
Project-URL: Repository, https://github.com/DeepLabCut/DeepLabCut-live
